uniqdeque.py
uniqdeque-0.1.0a0.dist-info/licenses/LICENSE
uniqdeque-0.1.0a0.dist-info/METADATA
uniqdeque-0.1.0a0.dist-info/WHEEL
uniqdeque-0.1.0a0.dist-info/top_level.txt
uniqdeque-0.1.0a0.dist-info/RECORD
