Metadata-Version: 2.4
Name: uniqdeque
Version: 0.1.0a0
Summary: A hybrid data structure combining a deque and a set (unique elements).
Author-email: Jifeng Wu <jifengwu2k@gmail.com>
License-Expression: MIT
Project-URL: Homepage, https://github.com/jifengwu2k/uniqdeque
Project-URL: Bug Tracker, https://github.com/jifengwu2k/uniqdeque/issues
Classifier: Programming Language :: Python :: 2
Classifier: Programming Language :: Python :: 3
Classifier: Operating System :: OS Independent
Requires-Python: >=2
License-File: LICENSE
Requires-Dist: typing; python_version < "3.5"
Dynamic: license-file
